wellsaid_mcp/__init__.py
wellsaid_mcp/ai_director.py
wellsaid_mcp/avatars.py
wellsaid_mcp/mcp_server.py
wellsaid_mcp/model.py
wellsaid_mcp/server.py
wellsaid_mcp/setup_claude_desktop.py
wellsaid_mcp/tts.py
wellsaid_mcp/utils.py
wellsaid_mcp-0.2.1.dist-info/licenses/LICENSE
wellsaid_mcp-0.2.1.dist-info/METADATA
wellsaid_mcp-0.2.1.dist-info/WHEEL
wellsaid_mcp-0.2.1.dist-info/entry_points.txt
wellsaid_mcp-0.2.1.dist-info/top_level.txt
wellsaid_mcp-0.2.1.dist-info/RECORD
