Metadata-Version: 2.4
Name: wellsaid-mcp
Version: 0.2.1
Summary: An MCP server for using Wellsaid Text-To-Speech APIs
Requires-Python: >=3.12
License-File: LICENSE
Requires-Dist: httpx>=0.26.0
Requires-Dist: python-dotenv>=1.0.1
Requires-Dist: pydantic>=2.6.0
Requires-Dist: fuzzywuzzy>=0.18.0
Requires-Dist: mcp>=1.12.4
Dynamic: license-file
